guillotina_audit/CHANGELOG.rst
guillotina_audit/__init__.py
guillotina_audit/api.py
guillotina_audit/install.py
guillotina_audit/interfaces.py
guillotina_audit/migrator.py
guillotina_audit/models.py
guillotina_audit/parser.py
guillotina_audit/permissions.py
guillotina_audit/subscriber.py
guillotina_audit/utility.py
guillotina_audit/commands/__init__.py
guillotina_audit/commands/mappings.py
guillotina_audit/commands/migrator.py
guillotina_audit/commands/settings.py
guillotina_audit/tests/conftest.py
guillotina_audit/tests/fixtures.py
guillotina_audit/tests/test_audit_basic.py
guillotina_audit/tests/test_mappings.py
guillotina_audit/tests/test_migrator.py
guillotina_audit/tests/test_package.py
guillotina_audit/tests/utils.py
guillotina_audit-2.0.11.dist-info/LICENSE
guillotina_audit-2.0.11.dist-info/METADATA
guillotina_audit-2.0.11.dist-info/WHEEL
guillotina_audit-2.0.11.dist-info/top_level.txt
guillotina_audit-2.0.11.dist-info/zip-safe
guillotina_audit-2.0.11.dist-info/RECORD
