Metadata-Version: 2.1
Name: guillotina_audit
Version: 2.0.11
Summary: elasticsearch audit support for guillotina
Home-page: https://github.com/guillotinaweb/guillotina_audit
Author: Nil Bacardit Vinyals
Author-email: n.bacardit@iskra.cat
License: GPL version 3
Keywords: search async guillotina elasticsearch audit
Classifier: Programming Language :: Python :: 3.7
Classifier: Programming Language :: Python :: 3.8
Classifier: Programming Language :: Python :: 3.9
Classifier: Programming Language :: Python :: 3.10
Classifier: Topic :: Software Development :: Libraries :: Python Modules
License-File: LICENSE
Requires-Dist: guillotina >=6.0.0a16
Requires-Dist: pydantic
Requires-Dist: elasticsearch[async] <=8.12.0,>=8.0.0
Provides-Extra: test
Requires-Dist: async-asgi-testclient ; extra == 'test'
Requires-Dist: pytest >=5.0 ; extra == 'test'
Requires-Dist: pytest-asyncio ==0.18.3 ; extra == 'test'
Requires-Dist: coverage ; extra == 'test'
Requires-Dist: pytest-cov ; extra == 'test'
Requires-Dist: pytest-docker-fixtures[pg] >=1.3.0 ; extra == 'test'
Requires-Dist: docker ; extra == 'test'
